phanas_pydantic_helpers/__init__.py
phanas_pydantic_helpers/common/__init__.py
phanas_pydantic_helpers/common/imports.py
phanas_pydantic_helpers/common/time.py
phanas_pydantic_helpers/common/typing.py
phanas_pydantic_helpers/fields/__init__.py
phanas_pydantic_helpers/fields/time.py
phanas_pydantic_helpers/helpers/__init__.py
phanas_pydantic_helpers/helpers/create_template_from_model.py
phanas_pydantic_helpers/helpers/factory.py
phanas_pydantic_helpers/helpers/field_converter.py
phanas_pydantic_helpers/helpers/misc.py
phanas_pydantic_helpers/helpers/validators.py
phanas_pydantic_helpers/version.py
phanas_pydantic_helpers-2.1.3.dist-info/LICENSE
phanas_pydantic_helpers-2.1.3.dist-info/WHEEL
phanas_pydantic_helpers-2.1.3.dist-info/METADATA
phanas_pydantic_helpers-2.1.3.dist-info/RECORD
