Metadata-Version: 2.1
Name: phanas-pydantic-helpers
Version: 2.1.3
Summary: A collection of helper functions/classes for Pydantic.
Home-page: https://github.com/Phanabani/phanas-pydantic-helpers
License: MIT
Keywords: pydantic,helper,helpers
Author: Phanabani
Author-email: phanabani@gmail.com
Requires-Python: >=3.7,<4.0
Classifier: License :: OSI Approved :: MIT License
Classifier: Programming Language :: Python :: 3
Classifier: Programming Language :: Python :: 3.7
Classifier: Programming Language :: Python :: 3.8
Classifier: Programming Language :: Python :: 3.9
Classifier: Programming Language :: Python :: 3.10
Classifier: Programming Language :: Python :: 3.11
Provides-Extra: time
Requires-Dist: pendulum (>=2.1.2,<3.0.0) ; extra == "time"
Requires-Dist: pydantic (>=1.10.4,<2.0.0)
Requires-Dist: pytimeparse (>=1.1.8,<2.0.0) ; extra == "time"
Requires-Dist: typing-extensions (>=4.4.0,<5.0.0)
Project-URL: Repository, https://github.com/Phanabani/phanas-pydantic-helpers
